pyhandlers/__init__.py
pyhandlers/handlers.py
pyhandlers/log_handlers.py
tests/__init__.py
pyhandlers-0.2.1.dist-info/LICENSE-MIT
pyhandlers-0.2.1.dist-info/METADATA
pyhandlers-0.2.1.dist-info/WHEEL
pyhandlers-0.2.1.dist-info/top_level.txt
pyhandlers-0.2.1.dist-info/RECORD
