Metadata-Version: 2.1
Name: pyhandlers
Version: 0.2.1
Summary: various utility/helper functions & decorators.
Home-page: https://github.com/bharathgs/pyhandlers
Author: Bharath G.S
Author-email: royalkingpin@gmail.com
Maintainer: Bharath G.S
Maintainer-email: royalkingpin@gmail.com
License: MIT
Keywords: error,handlers,decorators,utility,helpers
Platform: UNKNOWN
Classifier: Development Status :: 4 - Beta
Classifier: Intended Audience :: Developers
Classifier: License :: OSI Approved :: MIT License
Classifier: Natural Language :: English
Classifier: Operating System :: OS Independent
Classifier: Programming Language :: Python :: 3.6
Classifier: Programming Language :: Python :: Implementation :: CPython
